leon_mediacrawler/__init__.py
leon_mediacrawler/async_db.py
leon_mediacrawler/db.py
leon_mediacrawler/main.py
leon_mediacrawler/recv_sms.py
leon_mediacrawler/test_supabase.py
leon_mediacrawler/test_supabase_connection.py
leon_mediacrawler/test_supabase_simple.py
leon_mediacrawler/var.py
leon_mediacrawler/base/__init__.py
leon_mediacrawler/base/base_crawler.py
leon_mediacrawler/cache/__init__.py
leon_mediacrawler/cache/abs_cache.py
leon_mediacrawler/cache/cache_factory.py
leon_mediacrawler/cache/local_cache.py
leon_mediacrawler/cache/redis_cache.py
leon_mediacrawler/cmd_arg/__init__.py
leon_mediacrawler/cmd_arg/arg.py
leon_mediacrawler/config/__init__.py
leon_mediacrawler/config/base_config.py
leon_mediacrawler/config/db_config.py
leon_mediacrawler/config/supabase_config.py
leon_mediacrawler/constant/__init__.py
leon_mediacrawler/constant/baidu_tieba.py
leon_mediacrawler/constant/zhihu.py
leon_mediacrawler/docs/STZHONGS.TTF
leon_mediacrawler/docs/hit_stopwords.txt
leon_mediacrawler/docs/index.md
leon_mediacrawler/docs/mediacrawlerpro订阅.md
leon_mediacrawler/docs/代理使用.md
leon_mediacrawler/docs/作者介绍.md
leon_mediacrawler/docs/常见问题.md
leon_mediacrawler/docs/开发者咨询.md
leon_mediacrawler/docs/微信交流群.md
leon_mediacrawler/docs/手机号登录说明.md
leon_mediacrawler/docs/捐赠名单.md
leon_mediacrawler/docs/知识付费介绍.md
leon_mediacrawler/docs/知识星球介绍.md
leon_mediacrawler/docs/词云图使用配置.md
leon_mediacrawler/docs/项目代码结构.md
leon_mediacrawler/docs/static/images/11群二维码.JPG
leon_mediacrawler/docs/static/images/12群二维码.JPG
leon_mediacrawler/docs/static/images/13群二维码.JPG
leon_mediacrawler/docs/static/images/14群二维码.jpeg
leon_mediacrawler/docs/static/images/IP_提取图.png
leon_mediacrawler/docs/static/images/auto_test.png
leon_mediacrawler/docs/static/images/img.png
leon_mediacrawler/docs/static/images/img_1.png
leon_mediacrawler/docs/static/images/img_2.png
leon_mediacrawler/docs/static/images/img_3.png
leon_mediacrawler/docs/static/images/img_4.png
leon_mediacrawler/docs/static/images/relakkes_weichat.jpg
leon_mediacrawler-0.1.4.dist-info/licenses/LICENSE
leon_mediacrawler-0.1.4.dist-info/METADATA
leon_mediacrawler-0.1.4.dist-info/WHEEL
leon_mediacrawler-0.1.4.dist-info/entry_points.txt
leon_mediacrawler-0.1.4.dist-info/top_level.txt
leon_mediacrawler-0.1.4.dist-info/RECORD
