Metadata-Version: 2.4
Name: leon-mediacrawler
Version: 0.1.4
Summary: A social media crawler project, support Xiaohongshu, Weibo, Zhihu, Bilibili, Douyin, BaiduTieBa etc.
Author-email: Bradleon <bradleon91@gmail.com>
License: MIT
Project-URL: Homepage, https://github.com/BradLeon/MediaCrawler
Project-URL: Documentation, https://nanmicoder.github.io/MediaCrawler/
Project-URL: Repository, https://github.com/BradLeon/MediaCrawler
Project-URL: Issues, https://github.com/BradLeon/MediaCrawler/issues
Keywords: crawler,spider,social media,xiaohongshu,douyin,weibo,zhihu,bilibili
Classifier: Development Status :: 3 - Alpha
Classifier: Intended Audience :: Developers
Classifier: Programming Language :: Python :: 3
Classifier: Programming Language :: Python :: 3.9
Classifier: Programming Language :: Python :: 3.10
Classifier: Programming Language :: Python :: 3.11
Classifier: Topic :: Internet :: WWW/HTTP :: Browsers
Classifier: Topic :: Software Development :: Libraries :: Python Modules
Classifier: Operating System :: OS Independent
Requires-Python: >=3.9
License-File: LICENSE
Requires-Dist: aiofiles~=23.2.1
Requires-Dist: aiomysql==0.2.0
Requires-Dist: fastapi==0.110.2
Requires-Dist: httpx==0.27.0
Requires-Dist: jieba==0.42.1
Requires-Dist: matplotlib==3.9.0
Requires-Dist: opencv-python
Requires-Dist: pandas==2.2.3
Requires-Dist: parsel==1.9.1
Requires-Dist: pillow==10.0.0
Requires-Dist: playwright==1.42.0
Requires-Dist: pydantic==2.5.2
Requires-Dist: pyexecjs==1.5.1
Requires-Dist: python-dotenv==1.0.1
Requires-Dist: redis~=4.6.0
Requires-Dist: requests==2.32.3
Requires-Dist: tenacity==8.2.2
Requires-Dist: uvicorn==0.29.0
Requires-Dist: wordcloud==1.9.3
Requires-Dist: supabase==2.15.2
Requires-Dist: packaging>=20.0
Provides-Extra: dev
Requires-Dist: pytest; extra == "dev"
Requires-Dist: pytest-asyncio; extra == "dev"
Requires-Dist: black; extra == "dev"
Requires-Dist: flake8; extra == "dev"
Requires-Dist: mypy; extra == "dev"
Dynamic: license-file
